missingvalues/missing.py
missing_values-1.0.0.dist-info/LICENSE
missing_values-1.0.0.dist-info/METADATA
missing_values-1.0.0.dist-info/WHEEL
missing_values-1.0.0.dist-info/entry_points.txt
missing_values-1.0.0.dist-info/top_level.txt
missing_values-1.0.0.dist-info/RECORD
