Metadata-Version: 2.1
Name: missing-values
Version: 1.0.0
Summary: Handling missing values in dataset
Home-page: UNKNOWN
Author: Kartikey Tiwari
Author-email: kartikeytiwari37@gmail.com
License: MIT
Platform: UNKNOWN
Classifier: License :: OSI Approved :: MIT License
Classifier: Programming Language :: Python :: 3
Classifier: Programming Language :: Python :: 3.4
Classifier: Programming Language :: Python :: 3.5
Classifier: Programming Language :: Python :: 3.6
Classifier: Programming Language :: Python :: 3.7
Requires-Dist: numpy
Requires-Dist: pandas
